LICENSE
fsai_awrp/__init__.py
fsai_awrp/fsai_awrp.py
fsai_awrp-0.1.3.dist-info/LICENSE
fsai_awrp-0.1.3.dist-info/WHEEL
fsai_awrp-0.1.3.dist-info/METADATA
fsai_awrp-0.1.3.dist-info/RECORD
