Metadata-Version: 2.1
Name: fsai-awrp
Version: 0.1.3
Summary: Library that helps an application report progress to Argo Workflows.
Home-page: https://github.com/fsai-dev/fsai-awrp
License: MIT
Author: Michael Mohamed
Author-email: michael@foundationstack.com
Requires-Python: >=3.7.1,<4.0
Classifier: License :: OSI Approved :: MIT License
Classifier: Programming Language :: Python :: 3
Classifier: Programming Language :: Python :: 3.10
Classifier: Programming Language :: Python :: 3.8
Classifier: Programming Language :: Python :: 3.9
Requires-Dist: loguru (>=0.6.0,<0.7.0)
Project-URL: Repository, https://github.com/fsai-dev/fsai-awrp
